{
    "key": "group_64546da450c61",
    "title": "Block Google Map",
    "fields": [
        {
            "key": "field_64547d62283a3",
            "label": "Content",
            "name": "",
            "aria-label": "",
            "type": "tab",
            "instructions": "",
            "required": 0,
            "conditional_logic": 0,
            "wrapper": {
                "width": "",
                "class": "",
                "id": ""
            },
            "placement": "top",
            "endpoint": 0
        },
        {
            "key": "field_64546da578d30",
            "label": "Embed Google Map",
            "name": "location_google_map_block",
            "aria-label": "",
            "type": "textarea",
            "instructions": "",
            "required": 0,
            "conditional_logic": 0,
            "wrapper": {
                "width": "",
                "class": "",
                "id": ""
            },
            "default_value": "<iframe src=\"https:\/\/www.google.com\/maps\/embed?pb=!1m18!1m12!1m3!1d12429.190760047948!2d-76.93279697182639!3d38.848542234709626!2m3!1f0!2f0!3f0!3m2!1i1024!2i768!4f13.1!3m3!1m2!1s0x89b7b94bdfc0b7c5%3A0x1a3f4e1178933bbc!2sSuitland%2C+Suitland-Silver+Hill%2C+Maryland+20746!5e0!3m2!1svi!2s!4v1546841623730\" allowfullscreen><\/iframe>",
            "maxlength": "",
            "rows": "",
            "placeholder": "",
            "new_lines": ""
        },
        {
            "key": "field_64547d70283a4",
            "label": "Styles",
            "name": "",
            "aria-label": "",
            "type": "tab",
            "instructions": "",
            "required": 0,
            "conditional_logic": 0,
            "wrapper": {
                "width": "",
                "class": "",
                "id": ""
            },
            "placement": "top",
            "endpoint": 0
        },
        {
            "key": "field_64547d7d283a5",
            "label": "Height",
            "name": "height_google_map_block",
            "aria-label": "",
            "type": "number",
            "instructions": "",
            "required": 0,
            "conditional_logic": 0,
            "wrapper": {
                "width": "50",
                "class": "",
                "id": ""
            },
            "default_value": "",
            "min": 0,
            "max": 1000,
            "placeholder": "",
            "step": "",
            "prepend": "",
            "append": ""
        }
    ],
    "location": [
        [
            {
                "param": "block",
                "operator": "==",
                "value": "acf\/be-google-map"
            }
        ]
    ],
    "menu_order": 0,
    "position": "normal",
    "style": "default",
    "label_placement": "top",
    "instruction_placement": "label",
    "hide_on_screen": "",
    "active": true,
    "description": "",
    "show_in_rest": 0,
    "modified": 1688952383
}